setup.cfg
setup.py
pyzenodo/__init__.py
pyzenodo/zenodo.py
pyzenodo.egg-info/PKG-INFO
pyzenodo.egg-info/SOURCES.txt
pyzenodo.egg-info/dependency_links.txt
pyzenodo.egg-info/requires.txt
pyzenodo.egg-info/top_level.txt